{
	"name": "Copy_Data_UI_DW",
	"properties": {
		"activities": [
			{
				"name": "Babasaheb To Suhel",
				"type": "Copy",
				"dependsOn": [
					{
						"activity": "Get Metadata1",
						"dependencyConditions": [
							"Succeeded"
						]
					}
				],
				"policy": {
					"timeout": "0.12:00:00",
					"retry": 0,
					"retryIntervalInSeconds": 30,
					"secureOutput": false,
					"secureInput": false
				},
				"userProperties": [],
				"typeProperties": {
					"source": {
						"type": "DelimitedTextSource",
						"storeSettings": {
							"type": "AzureBlobFSReadSettings",
							"recursive": true,
							"enablePartitionDiscovery": false
						},
						"formatSettings": {
							"type": "DelimitedTextReadSettings"
						}
					},
					"sink": {
						"type": "DelimitedTextSink",
						"storeSettings": {
							"type": "AzureBlobFSWriteSettings"
						},
						"formatSettings": {
							"type": "DelimitedTextWriteSettings",
							"quoteAllText": true,
							"fileExtension": ".txt"
						}
					},
					"enableStaging": false,
					"translator": {
						"type": "TabularTranslator",
						"mappings": [
							{
								"source": {
									"name": "ORDERNUMBER",
									"type": "String",
									"physicalType": "String"
								},
								"sink": {
									"name": "ORDERNUMBER",
									"type": "String",
									"physicalType": "String"
								}
							},
							{
								"source": {
									"name": "QUANTITYORDERED",
									"type": "String",
									"physicalType": "String"
								},
								"sink": {
									"name": "QUANTITYORDERED",
									"type": "String",
									"physicalType": "String"
								}
							},
							{
								"source": {
									"name": "PRICEEACH",
									"type": "String",
									"physicalType": "String"
								},
								"sink": {
									"name": "PRICEEACH",
									"type": "String",
									"physicalType": "String"
								}
							},
							{
								"source": {
									"name": "ORDERLINENUMBER",
									"type": "String",
									"physicalType": "String"
								},
								"sink": {
									"name": "ORDERLINENUMBER",
									"type": "String",
									"physicalType": "String"
								}
							},
							{
								"source": {
									"name": "SALES",
									"type": "String",
									"physicalType": "String"
								},
								"sink": {
									"name": "SALES",
									"type": "String",
									"physicalType": "String"
								}
							},
							{
								"source": {
									"name": "ORDERDATE",
									"type": "String",
									"physicalType": "String"
								},
								"sink": {
									"name": "ORDERDATE",
									"type": "String",
									"physicalType": "String"
								}
							},
							{
								"source": {
									"name": "STATUS",
									"type": "String",
									"physicalType": "String"
								},
								"sink": {
									"name": "STATUS",
									"type": "String",
									"physicalType": "String"
								}
							},
							{
								"source": {
									"name": "QTR_ID",
									"type": "String",
									"physicalType": "String"
								},
								"sink": {
									"name": "QTR_ID",
									"type": "String",
									"physicalType": "String"
								}
							},
							{
								"source": {
									"name": "MONTH_ID",
									"type": "String",
									"physicalType": "String"
								},
								"sink": {
									"name": "MONTH_ID",
									"type": "String",
									"physicalType": "String"
								}
							},
							{
								"source": {
									"name": "YEAR_ID",
									"type": "String",
									"physicalType": "String"
								},
								"sink": {
									"name": "YEAR_ID",
									"type": "String",
									"physicalType": "String"
								}
							}
						],
						"typeConversion": true,
						"typeConversionSettings": {
							"allowDataTruncation": true,
							"treatBooleanAsNumber": false
						}
					}
				},
				"inputs": [
					{
						"referenceName": "DelimitedText1",
						"type": "DatasetReference",
						"parameters": {
							"Container_Name": "user-input-container",
							"Folder_Name": "Babasaheb",
							"File_Name": "sales_data.csv"
						}
					}
				],
				"outputs": [
					{
						"referenceName": "DelimitedText1",
						"type": "DatasetReference",
						"parameters": {
							"Container_Name": "user-input-container",
							"Folder_Name": "Suhel",
							"File_Name": "SuhelKings.csv"
						}
					}
				]
			},
			{
				"name": "Get Metadata1",
				"type": "GetMetadata",
				"dependsOn": [],
				"policy": {
					"timeout": "0.12:00:00",
					"retry": 0,
					"retryIntervalInSeconds": 30,
					"secureOutput": false,
					"secureInput": false
				},
				"userProperties": [],
				"typeProperties": {
					"dataset": {
						"referenceName": "DelimitedText1",
						"type": "DatasetReference",
						"parameters": {
							"Container_Name": {
								"value": "@pipeline().parameters.CN",
								"type": "Expression"
							},
							"Folder_Name": {
								"value": "@pipeline().parameters.FDN",
								"type": "Expression"
							},
							"File_Name": {
								"value": "@trim('')",
								"type": "Expression"
							}
						}
					},
					"fieldList": [
						"childItems"
					],
					"storeSettings": {
						"type": "AzureBlobFSReadSettings",
						"enablePartitionDiscovery": false
					},
					"formatSettings": {
						"type": "DelimitedTextReadSettings"
					}
				}
			},
			{
				"name": "Get Metadata1_copy1",
				"type": "GetMetadata",
				"dependsOn": [
					{
						"activity": "Babasaheb To Suhel",
						"dependencyConditions": [
							"Succeeded"
						]
					}
				],
				"policy": {
					"timeout": "0.12:00:00",
					"retry": 0,
					"retryIntervalInSeconds": 30,
					"secureOutput": false,
					"secureInput": false
				},
				"userProperties": [],
				"typeProperties": {
					"dataset": {
						"referenceName": "DelimitedText1",
						"type": "DatasetReference",
						"parameters": {
							"Container_Name": {
								"value": "@pipeline().parameters.CN",
								"type": "Expression"
							},
							"Folder_Name": {
								"value": "@pipeline().parameters.FDN",
								"type": "Expression"
							},
							"File_Name": {
								"value": "@trim('')",
								"type": "Expression"
							}
						}
					},
					"fieldList": [
						"childItems"
					],
					"storeSettings": {
						"type": "AzureBlobFSReadSettings",
						"enablePartitionDiscovery": false
					},
					"formatSettings": {
						"type": "DelimitedTextReadSettings"
					}
				}
			}
		],
		"parameters": {
			"FN": {
				"type": "string"
			},
			"FDN": {
				"type": "string",
				"defaultValue": "Suhel"
			},
			"CN": {
				"type": "string",
				"defaultValue": "user-input-container"
			}
		},
		"annotations": []
	}
}